perfana/__init__.py
perfana/_version.py
perfana/conversions.py
perfana/exceptions.py
perfana/types.py
perfana/core/__init__.py
perfana/core/relative.py
perfana/core/returns.py
perfana/core/risk.py
perfana/core/utils.py
perfana/datasets/__init__.py
perfana/datasets/_file_handler.py
perfana/datasets/base.py
perfana/monte_carlo/__init__.py
perfana/monte_carlo/_types.py
perfana/monte_carlo/_utility.py
perfana/monte_carlo/ratios.py
perfana/monte_carlo/returns.py
perfana/monte_carlo/risk.py
perfana/monte_carlo/sensitivity.py
perfana/pd_ext/__init__.py
perfana/pd_ext/frame.py
perfana/pd_ext/series.py
perfana/utils/__init__.py
perfana/utils/cache.py
perfana-0.0.8.dist-info/METADATA
perfana-0.0.8.dist-info/WHEEL
perfana-0.0.8.dist-info/top_level.txt
perfana-0.0.8.dist-info/RECORD
