Metadata-Version: 2.1
Name: perfana
Version: 0.0.8
Summary: Toolbox for performance and portfolio analytics
Home-page: https://github.com/DanielBok/perfana
Author: Daniel Bok
Author-email: daniel.bok@outlook.com
License: MIT
Platform: UNKNOWN
Classifier: Development Status :: 3 - Alpha
Classifier: Intended Audience :: End Users/Desktop
Classifier: Intended Audience :: Financial and Insurance Industry
Classifier: Programming Language :: Python
Classifier: Programming Language :: Python :: 3
Classifier: Programming Language :: Python :: 3.7
Requires-Python: >=3.7
Requires-Dist: copulae (>=0.4)
Requires-Dist: numpy
Requires-Dist: pandas (>=0.23)
Provides-Extra: plot
Requires-Dist: matplotlib ; extra == 'plot'
